steamplus
