Metadata-Version: 2.1
Name: steamplus
Version: 0.3.1
Summary: A library for extracting data from steam via steam storefront api and steamspy api
Home-page: https://github.com/MartijnCBV/steamplus/wiki
Author: Team Ster
Author-email: martijn.business@hotmail.com
License: GPL-3.0-only
Download-URL: https://github.com/MartijnCBV/steamplus/archive/0.3.1.tar.gz
Keywords: steam,statistics,valve
Platform: UNKNOWN
Classifier: Development Status :: 3 - Alpha
Classifier: Intended Audience :: Developers
Classifier: Programming Language :: Python :: 3
Classifier: Operating System :: OS Independent
Classifier: License :: OSI Approved :: GNU General Public License v3 (GPLv3)
Classifier: Natural Language :: English
Classifier: Topic :: Games/Entertainment
Requires-Python: >=3.8
